{
	"icon-prefix": "ai",
	"icon-class": "ai-deadline",
	"icon-size": "",
	"icon-extra-class": "",
	"icon-text": "",
	"icon-id": false,
	"sr-only": false,
	"aria-hidden": false,
	"icon-pre-text": false,
	"icon-post-text": false,
	"icon-title": false,
	"icon-sr-only-text": false,
	"link-text": "En lenke ser slik ut",
	"link-url": "/patterns/04-sider-01-forside-00-forside/04-sider-01-forside-00-forside.html",
	"sr-text": false,
	"dateDay": "20",
	"dateMonth": "feb",
	"hasIcon": {
		"icon-prefix": "ai",
		"icon-class": "ai-server",
		"icon-extra-class": "a-icon a-icon-circle"
	},
	"hasTextSmall": false,
	"icontext": "Dette er tittelen p책 modalen",
	"variation-class": "a-iconText-background a-iconText-large",
	"isHeader": true,
	"button-text": "En standard knapp",
	"button-class": "a-modal-back",
	"button-disabled": false,
	"button-type": "button",
	"onclick": false,
	"button-icon": false,
	"display-as-link": false,
	"aria-label": "Tilbake",
	"button-list": [
		{
			"button-class": "a-modal-back",
			"aria-label": "G책 tilbake",
			"onclick": false,
			"enable-popover": false,
			"icon-prefix": "ai",
			"icon-class": "ai-back",
			"icon-extra-class": "a-modal-back-icon"
		},
		{
			"button-class": "a-modal-close",
			"aria-label": "Lukk",
			"onclick": false,
			"enable-popover": false,
			"icon-prefix": "ai",
			"icon-class": "ai-exit",
			"icon-extra-class": "a-modal-close-icon"
		}
	],
	"login-name": "JAN PETTERSEN",
	"display-as-dropdown": false,
	"personlogin-isDropdown": "dropdown",
	"login-icon": {
		"icon-prefix": "ai",
		"icon-class": "ai-private-circle-big",
		"icon-extra-class": "a-personSwitcher-icon a-js-onboardingTarget-1"
	},
	"logo": "../../images/a-logo-white.svg",
	"logo-class": "a-modal-top-logo",
	"show-login": false,
	"neutral-logo": {
		"logo": "../../images/a-logo-white.svg"
	},
	"login-show": {
		"login-name": "JAN PETTERSEN",
		"login-icon": {
			"icon-prefix": "ai",
			"icon-class": "ai-private-circle-big",
			"icon-extra-class": "a-personSwitcher-icon"
		}
	},
	"modal-id": "modalExample",
	"modal-launch-title": "Start modal",
	"modalprosess-navbar": {
		"button-list": [
			{
				"button-class": "a-modal-back",
				"aria-label": "G책 tilbake",
				"onclick": "goBack()",
				"enable-popover": false,
				"icon-prefix": "ai",
				"icon-class": "ai-back",
				"icon-extra-class": "a-modal-back-icon"
			},
			{
				"button-class": "a-modal-close",
				"aria-label": "Lukk",
				"icon-prefix": "ai",
				"icon-class": "ai-exit",
				"icon-extra-class": "a-modal-close-icon",
				"onclick": false,
				"enable-popover": true,
				"popover-placement": "bottom",
				"popover-content-id": "sampleIdPopover",
				"popover-class": "popover-warning",
				"popover-text": "Er du sikker p책 at du vil avslutte registrering av Enkeltpersonforetak?",
				"popover-buttons": [
					{
						"button-text": "Ja, avslutt.",
						"button-class": "a-btn a-btn-danger",
						"onclick": "location.href='../../patterns/04-sider-10-seksjonsforsider-30-seksjonsforside-v-starteogdrive/04-sider-10-seksjonsforsider-30-seksjonsforside-v-starteogdrive.html'"
					},
					{
						"button-text": "Fortsett",
						"button-class": "a-btn-link a-linkDanger",
						"display-as-link": true,
						"onclick": "$('button[aria-describedby=' + $(this).parent().parent().attr('id') + ']').click();"
					}
				]
			}
		]
	},
	"modal-title": "Gi og fjerne rettigheter (2)",
	"modal-content": "Dette er det ANDRE steget i prosessen. Lorem ipsum dolor sit amet, consectetur adipisicing elit. Ea sint dicta hic illo repellat saepe reprehenderit, non sed corporis neque exercitationem minima ullam nobis necessitatibus at in libero, iure alias!",
	"modal-nextbutton": {
		"link-text": "Neste",
		"link-class": "a-btn",
		"link-url": "/patterns/04-sider-80-prosess-70-prosess-2/04-sider-80-prosess-70-prosess-2.html"
	},
	"modal-successbutton": {
		"link-text": "Hvis du klarer det",
		"link-url": "/patterns/04-sider-80-prosess-70-prosess-ferdig/04-sider-80-prosess-70-prosess-ferdig.html",
		"link-class": "a-btn a-btn-success"
	},
	"modal-startover": false,
	"modal-errorbutton": {
		"link-text": "Hvis du ikke klarer det",
		"link-url": "/patterns/04-sider-80-prosess-70-prosess-feil/04-sider-80-prosess-70-prosess-feil.html",
		"link-class": "a-btn a-btn-danger"
	},
	"modal-discard": {
		"link-text": "Avbryt",
		"link-url": ""
	},
	"animationClass": "a-scene-element--fadeinright",
	"title": "Altinn",
	"bodyClass": "a-modal-background",
	"header-color": "a-darkBackground",
	"modalBack": true
}