{
  "modal-starte-enk": {
    "_commentStart": "--------------------------------------------------------------",
    "_commentText": "CHAT",
    "_commentEnd": "--------------------------------------------------------------",
    "bodyClass": "a-modal-background a-js-lookup",
    "logo": "../../images/a-logo-white.svg",
    "login-name": "Jan Pettersen",
    "animationClass": "a-scene_element--fadeinright",
    "starteenk-back": {
      "btn-url": "link.sider-starte-enk-1"
    },
    "header-color": "a-darkBackground",
    "modalBack": false,
    "modalHeader-icon": "&#xE0AF;",
    "isIntroText": {
      "modalHeader-introText": "Brønnøysundregistrene SIDE"
    },
    "modalHeader-title": "Starte Enkeltpersonforetak",
    "modalHeader-title-code": "(ENK)",
    "modal-title": {
      "section-title": "Hva skal du drive med?",
      "titleExtra": {
        "titleExtra-text": "(Skriv stikkord så foreslår vi næringskoder)"
      }
    },
    "modal-lead": false,
    "modal-input-orgName": {
      "isValidator": "",
      "input-label-class": "sr-only",
      "input-type": "text",
      "text-input-id": "bransje",
      "isLarge": "a-form-group-large",
      "isHidden": "sr-only",
      "text-input-label": "Bransje:",
      "text-input-placeholder": "f.eks tekstil, fotografering, webdesign.."
    },
    "modal-loader": true,
    "modal-empty": {
      "paragraph-class": "a-js-noResults",
      "paragraph-content": "Ingen treff."
    },
    "modal-validatorInfo": false,
    "modal-validatorInfoOK": false,
    "modal-input-textArea": false,
    "modal-input-radio": false,
    "modal-date": false,
    "modal-chooseCategory": {
      "radio-id": "a-js-radio-bransje",
      "radio-legend": {
        "radio-legendText": "Våre forslag:",
        "titleExtra": {
          "titleExtra-text": "(hvis ingen passer kan du prøve nytt stikkord)"
        }
      },
      "radio-stacked": "custom-controls-stacked",
      "radio-class": "a-radioButtons-stackedList a-radioButtons-searchResult",
      "radiobuttons": [
        {
          "radiobutton-title": "%PATH% <span style='color:#000'>%NAME%</span>",
          "radiobutton-id": "%ID%",
          "radiobuttons-excerpt": {
            "radiobuttons-excerptText": "%DESCRIPTION%"
          }
        }
      ]
    },
    "modal-input-adress": false,
    "modal-nextbutton": {
      "button-text": "Velg næringskode",
      "link-url": "link.sider-starte-enk-4",
      "button-class": "a-btn"
    },
    "modal-successbutton": false,
    "modal-deactivated": false,
    "modal-discard": {
      "button-text": "Jeg vil finne næringskode selv",
      "button-class": "a-btn-link"
    },
    "modal-extraInfo": {
      "bullet-list-items": [
        {
          "list-item-description": "Her finner vi næringskode for virksomheten din. Dette blir brukt av SSB til statistikk. Det kan også være utslagsgivende for hvilken støtte og fradrag du har rett på."
        },
        {
          "list-item-description": "Mange har deler av virksomheten som passer i forskjellige kategorier. Velg stikkord som beskriver kjernevirksomheten."
        }
      ]
    },
    "help-text-1": "Står du fast? Start en",
    "is-chat": true,
    "help-text-2": " eller ring oss på",
    "help-text-icon": "<i class='fa fa-life-ring'>",
    "help-link-2": {
      "link-text": "75 00 60 00",
      "link-url": "tel:+47 75 00 60 00"
    },
    "input-chat": {
      "text-input-id": "text-input-search-11",
      "text-input-label": "Ditt spørsmål her",
      "text-input-placeholder": "Ditt spørsmål her",
      "input-type": "text",
      "isHidden": "sr-only",
      "isInput-group": "input-group",
      "form-label-class": "input-group-addon",
      "form-input-hasButton-class": "form-control-noAddon",
      "form-input-hasButton": {
        "form-input-button-action": "Send",
        "form-input-button-icon": "&#xE163;",
        "form-input-button-iconClass": "material-icons"
      }
    }
  }
}
