{
	"icon-prefix": "ai",
	"icon-class": "ai-plus",
	"icon-size": "ai-lg",
	"icon-extra-class": "a-box-button-icon a-blueDarkText",
	"icon-text": "",
	"icon-id": false,
	"sr-only": false,
	"aria-hidden": false,
	"stacked-background": false,
	"icon-post-text": false,
	"icon-title": false,
	"icon-sr-only-text": false,
	"themeCss": "../../css/style.prototype.altinn.css",
	"themeJs": "./../../js/altinnPrototyping.js",
	"themeJsVendor": "../../js/altinnPrototyping.vendor.js",
	"box-button-add-textover": "Legg til ny person",
	"box-button-add-textunder": "eller virksomhet"
}