{
  "path-items": [
    {
      "path-label": "Et hakk opp",
      "path-link": true
    },
    {
      "path-label": "Denne katalogen"
    }
  ],
  "document-list-items": [
    {
      "document-name": "Dokumentasjon",
      "document-author": "Per Person",
      "document-date": {
        "day": 22,
        "month": "02",
        "year": 2020,
        "time": "13:58"
      },
      "folder": true,
      "icon-main": {
        "icon-prefix": "reg",
        "icon-class": "reg-closedfolder ai-md"
      },
      "icon-hover": {
        "icon-prefix": "reg",
        "icon-class": "reg-openfolder ai-md"
      }
    },
    {
      "document-name": "Dokument.txt",
      "document-author": "Per Person",
      "document-date": {
        "day": 22,
        "month": "02",
        "year": 2020,
        "time": "13:58"
      },
      "icon-main": {
        "icon-prefix": "reg",
        "icon-class": "reg-attachment ai-md"
      },
      "icon-hover": {
        "icon-prefix": "reg",
        "icon-class": "reg-download ai-md"
      }
    },
    {
      "document-name": "Dokument.pdf",
      "document-author": "Per Person",
      "document-date": {
        "day": 22,
        "month": "02",
        "year": 2020,
        "time": "13:58"
      },
      "icon-main": {
        "icon-prefix": "reg",
        "icon-class": "reg-attachment-pdf ai-md"
      },
      "icon-hover": {
        "icon-prefix": "reg",
        "icon-class": "reg-download ai-md"
      }
    },
    {
      "document-name": "Dokument.csv",
      "document-author": "Per Person",
      "document-date": {
        "day": 22,
        "month": "02",
        "year": 2020,
        "time": "13:58"
      },
      "icon-main": {
        "icon-prefix": "reg",
        "icon-class": "reg-attachment-csv ai-md"
      },
      "icon-hover": {
        "icon-prefix": "reg",
        "icon-class": "reg-download ai-md"
      }
    },
    {
      "document-name": "Dokument.ods",
      "document-author": "Per Person",
      "document-date": {
        "day": 22,
        "month": "02",
        "year": 2020,
        "time": "13:58"
      },
      "icon-main": {
        "icon-prefix": "reg",
        "icon-class": "reg-attachment-ods ai-md"
      },
      "icon-hover": {
        "icon-prefix": "reg",
        "icon-class": "reg-download ai-md"
      }
    },
    {
      "document-name": "Dokument.xml",
      "document-author": "Per Person",
      "document-date": {
        "day": 22,
        "month": "02",
        "year": 2020,
        "time": "13:58"
      },
      "icon-main": {
        "icon-prefix": "reg",
        "icon-class": "reg-attachment-xml ai-md"
      },
      "icon-hover": {
        "icon-prefix": "reg",
        "icon-class": "reg-download ai-md"
      }
    }
  ]
}