{
	"title" : "Altinn",
	"bodyClass": "a-modal-background",
	"logo" : "../../images/a-logo-white.svg",
	"header-color" : "a-darkBackground",
	"modalBack": false,

	"animationClass" : "a-scene_element--fadeinright",

	"modal-title" : "Gi og fjerne rettigheter (1)",
	"modal-content" : "Dette er det FØRSTE steget i prosessen. Lorem ipsum dolor sit amet, consectetur adipisicing elit. Ea sint dicta hic illo repellat saepe reprehenderit, non sed corporis neque exercitationem minima ullam nobis necessitatibus at in libero, iure alias!",

	"modal-nextbutton" : {
		"link-text" : "Neste",
		"link-url" : "link.sider-prosess-2",
		"link-class" : "a-btn"
	},
	"modal-successbutton" : false,
	"modal-errorbutton" : false,
	"modal-discard" : {
		"link-text" : "Avbryt",
		"link-url" : "link.sider-forside"
	}

}
