{
	"icon-prefix": "ai",
	"icon-class": "ai-private",
	"icon-size": "",
	"icon-extra-class": "hidden-md-down",
	"icon-text": "",
	"icon-id": false,
	"sr-only": false,
	"aria-hidden": false,
	"stacked-background": false,
	"icon-post-text": false,
	"icon-title": false,
	"icon-sr-only-text": false,
	"themeCss": "../../css/style.prototype.altinn.css",
	"themeJs": "./../../js/altinnPrototyping.js",
	"themeJsVendor": "../../js/altinnPrototyping.vendor.js",
	"dropdown-name": "KARI NORDMANNS FORETAK",
	"dropdown-number": "995 644 944",
	"dropdown-number-prefix": "org. nr.",
	"isTransparent": true,
	"show-label": true,
	"label-text": "For:",
	"dropdown-items": [
		{
			"icon-prefix": "ai",
			"icon-class": "ai-private",
			"icon-extra-class": "hidden-md-down",
			"dropdown-item-name": "KARI NORDMANN",
			"dropdown-item-number": "",
			"value": 1
		},
		{
			"icon-prefix": "ai",
			"icon-class": "ai-private",
			"icon-extra-class": "hidden-md-down",
			"dropdown-item-name": "OLA NORDMANN",
			"dropdown-item-number": "",
			"value": 2
		},
		{
			"icon-prefix": "ai",
			"icon-class": "ai-client",
			"icon-extra-class": "hidden-md-down",
			"dropdown-item-name": "OLA NORDMANNS FORETAK",
			"dropdown-item-number-prefix": "org. nr.",
			"dropdown-item-number": "995 644 944",
			"value": 3
		},
		{
			"icon-prefix": "ai",
			"icon-class": "ai-client",
			"icon-extra-class": "hidden-md-down",
			"dropdown-item-name": "OLA NORDMANNS ANDRE FORETAK",
			"dropdown-item-number-prefix": "org. nr.",
			"dropdown-item-number": "995 644 944",
			"value": 4
		}
	]
}