{
	"icon-prefix": "ai",
	"icon-class": "ai-deadline",
	"icon-size": "",
	"icon-extra-class": "",
	"icon-text": "",
	"icon-id": false,
	"sr-only": false,
	"aria-hidden": false,
	"stacked-background": false,
	"icon-post-text": false,
	"icon-title": false,
	"icon-sr-only-text": false,
	"link-text": "En lenke ser slik ut",
	"link-url": "/patterns/04-sider-infoportal-01-forside-00-forside/04-sider-infoportal-01-forside-00-forside.html",
	"sr-text": false,
	"hasFieldset": true,
	"switch-legend": "Velg et alternativ",
	"radiobuttons": [
		{
			"radiobuttons-title": "Du kan velge denne",
			"radiobuttons-id": "radiobutton-read",
			"radiobuttons-name": "addRights",
			"radiobuttons-class": "",
			"hasIcon": {
				"icon-prefix": "ai",
				"icon-class": "ai-read"
			}
		},
		{
			"radiobuttons-title": "eller denne",
			"radiobuttons-id": "radiobutton-edit",
			"radiobuttons-name": "addRights",
			"radiobuttons-class": "",
			"hasIcon": false
		},
		{
			"radiobuttons-title": "eller denne",
			"radiobuttons-id": "radiobutton-sign",
			"radiobuttons-name": "addRights",
			"radiobuttons-class": "",
			"hasIcon": false
		}
	]
}