{
  "collapseID": "andremedrettigheter",
  "collapse-panel-header-id": "othersWithRightsHeader",
  "isLarge": "a-collapsePanel--large",
  "dataParent": "#accordion",
  "collapseHeader": {
    "variation-class": "a-iconText-shadow a-iconText-large a-collapseBtn collapsed",
    "hasIcon": {
      "icon-prefix": "reg",
      "icon-class": "reg-corp",
      "icon-extra-class": "a-icon"
    },
    "hasTextSmall": false,
    "icontext": "Andre med rettigheter"
  },
  "button-class": "a-box-button",
  "box-list-id": "boxList",
  "activity-log": {
    "link-text": "Aktivitetslogg",
    "link-url": "/patterns/04-sider-portal-92-andre-med-rettigheter-00-andre-med-rettigheter-aktivitetslogg/04-sider-portal-92-andre-med-rettigheter-00-andre-med-rettigheter-aktivitetslogg.html"
  },
  "link-icon": "",
  "link-url": "/patterns/04-sider-portal-01-forside-00-forside/04-sider-portal-01-forside-00-forside.html",
  "box-button-list": [
    {
      "data-target": false,
      "has-children": false,
      "box-button-top-icon": {
        "icon-prefix": "ai",
        "icon-class": "ai-circle-exclamation",
        "icon-size": "ai-sm",
        "icon-extra-class": "a-danger a-noHover ai-top ai-float-right"
      },
      "box-button-title": false,
      "box-button-person": "PERNILLE HALL",
      "box-button-action": "Behandle forespørsel",
      "icon-prefix": "ai",
      "icon-class": "ai-private",
      "icon-size": "ai-lg",
      "icon-extra-class": "a-box-button-icon a-blueDarkText",
      "onclick": "location.href='link.sider-portal-andre-med-rettigheter-tilgangsforesporsel';"
    },
    {
      "data-target": false,
      "has-children": false,
      "box-button-top-icon": {
        "icon-prefix": "ai",
        "icon-class": "ai-circle-exclamation",
        "icon-size": "ai-sm",
        "icon-extra-class": "a-danger a-noHover ai-top ai-float-right"
      },
      "box-button-title": false,
      "box-button-person": "TUVA LANDRO",
      "box-button-action": "Behandle forespørsel",
      "icon-prefix": "ai",
      "icon-class": "ai-private",
      "icon-size": "ai-lg",
      "icon-extra-class": "a-box-button-icon a-blueDarkText",
      "onclick": "location.href='link.sider-portal-andre-med-rettigheter-tilgangsforesporsel-ikke-gjennomforbar';"
    },
    {
      "data-target": false,
      "has-children": false,
      "box-button-title": "REGNSKAPSFØRER",
      "box-button-person": "PERNILLE HALL",
      "box-button-action": "Gi og fjerne rettigheter",
      "icon-prefix": "ai",
      "icon-class": "ai-private",
      "icon-size": "ai-lg",
      "icon-extra-class": "a-box-button-icon a-blueDarkText",
      "onclick": "location.href='link.sider-portal-andre-med-rettigheter-roller-oversikt';"
    },
    {
      "data-target": false,
      "has-children": false,
      "box-button-title": "STYRE LEDER",
      "box-button-person": "TUVA LANDRO",
      "box-button-action": "Gi og fjerne rettigheter",
      "icon-prefix": "ai",
      "icon-class": "ai-private",
      "icon-size": "ai-lg",
      "icon-extra-class": "a-box-button-icon a-blueDarkText",
      "onclick": "location.href='link.sider-portal-andre-med-rettigheter-roller-oversikt';"
    },
    {
      "data-target": false,
      "has-children": false,
      "box-button-title": "DAGLIG LEDER",
      "box-button-person": "INGRID AGA",
      "box-button-action": "Gi og fjerne rettigheter",
      "icon-prefix": "ai",
      "icon-class": "ai-private",
      "icon-size": "ai-lg",
      "icon-extra-class": "a-box-button-icon a-blueDarkText",
      "onclick": "location.href='link.sider-portal-andre-med-rettigheter-roller-oversikt';"
    },
    {
      "data-target": false,
      "has-children": false,
      "box-button-title": "REGNSKAPSFØRER",
      "tooltip-name": "Julius Andreas Gimli Arn MacGyver Chewbacka Highlander Elessar-Jankov",
      "box-button-person": "Julius Andreas Gimli Arn MacGyver Chewbacka Highlander Elessar-Jankov",
      "box-button-action": "Gi og fjerne rettigheter",
      "icon-prefix": "ai",
      "icon-class": "ai-private",
      "icon-size": "ai-lg",
      "icon-extra-class": "a-box-button-icon a-blueDarkText",
      "onclick": "location.href='link.sider-portal-andre-med-rettigheter-roller-oversikt';"
    },
    {
      "box-button-title": "REVISOR",
      "box-button-person": "FJELLSTRAND REGNSKAP",
      "icon-prefix": "ai",
      "icon-class": "ai-corp",
      "icon-size": "ai-lg",
      "icon-extra-class": "a-box-button-icon",
      "box-button-action": "Se alle med rettigheter",
      "box-button-secondary-action": "Skjul alle med rettigheter",
      "data-target": "firstChildContainer",
      "has-children": true,
      "child-boxes-container-id": "firstChildContainer",
      "child-box-buttons": [
        {
          "data-target": false,
          "has-children": false,
          "box-button-title": "REVISOR",
          "box-button-person": "FJELLSTRAND REGNSKAP",
          "box-button-action": "Gi og fjerne rettigheter",
          "icon-prefix": "ai",
          "icon-class": "ai-corp",
          "icon-size": "ai-lg",
          "icon-extra-class": "a-box-button-icon a-blueDarkText",
          "onclick": "location.href='link.sider-portal-andre-med-rettigheter-roller-oversikt';"
        },
        {
          "data-target": false,
          "has-children": false,
          "box-button-title": "REVISOR",
          "box-button-person": "KENNETH HOGNESTAD",
          "box-button-action": "Gi og fjerne rettigheter",
          "icon-prefix": "ai",
          "icon-class": "ai-private",
          "icon-size": "ai-lg",
          "icon-extra-class": "a-box-button-icon a-blueDarkText",
          "onclick": "location.href='link.sider-portal-andre-med-rettigheter-roller-oversikt';"
        },
        {
          "data-target": false,
          "has-children": false,
          "box-button-title": "REVISOR",
          "box-button-person": "LISE GAUSDAL",
          "box-button-action": "Gi og fjerne rettigheter",
          "icon-prefix": "ai",
          "icon-class": "ai-private",
          "icon-size": "ai-lg",
          "icon-extra-class": "a-box-button-icon a-blueDarkText",
          "onclick": "location.href='link.sider-portal-andre-med-rettigheter-roller-oversikt';"
        }
      ]
    }
  ],
  "box-button-list-add": {
    "box-button-add-textover": "Legg til person",
    "box-button-add-textunder": "eller virksomhet",
    "icon-prefix": "ai",
    "icon-class": "ai-plus",
    "icon-size": "ai-lg",
    "icon-extra-class": "a-box-button-icon a-blueDarkText",
    "onclick": "location.href='link.sider-portal-andre-med-rettigheter-legg-til';"
  },
  "empty-rights": {
    "alert-id": "alert-no-arrow",
    "alert-class": "a-message-info a-message--arrow-off a-message--fullwidth",
    "alert-content": "Hvis du vil at andre skal hjelpe deg med å fylle ut skjema eller tjenester, kan du legge dem til her. Du velger også hva de skal ta rettigheter til å gjøre.",
    "button-class": "a-btn a-btn-action a-fullWidthBtn py-1",
    "action-button-text": "Legg til ny person eller virksomhet",
    "icon-prefix": "ai",
    "icon-class": "ai-plus",
    "icon-extra-class": "",
    "icon-text": ""
   }
}
