{
	"label-class": "badge-primary",
	"label-id": "label",
	"label-content": "9",
	"icon-prefix": "ai",
	"icon-class": "ai-deadline",
	"icon-size": "",
	"icon-extra-class": "",
	"icon-text": "",
	"icon-id": false,
	"sr-only": false,
	"aria-hidden": false,
	"stacked-background": false,
	"icon-post-text": false,
	"icon-title": false,
	"icon-sr-only-text": false,
	"button-text": "En knapp med ikon og skygge",
	"button-class": "a-btn a-btn-icon a-btn-shadow a-btn-shadow-large",
	"button-colorClass": "",
	"link-url": "",
	"button-shadow-label": false,
	"button-icon": {
		"icon-prefix": "ai",
		"icon-class": "ai-plus"
	},
	"button-text-second": {
		"button-text-second": "og mer tekst under her"
	},
	"button-dot": {
		"dot-color": "a-dot-red"
	}
}