{
  "has-popover-link" : {
    "popover-link-text": "",
    "popover-link-icon":
      [
      {
        "icon-prefix": "tmp",
        "icon-class": "tmp-help"
      },
      {
        "icon-prefix": "tmp",
        "icon-class": "tmp-cancel"
      }
    ],
    "open-popover-class": "a-helpIconButton a-js-persistPopover a-js-popoverBig a-js-togglePopoverIcons",
    "popover-class": "popover-big",
    "popover-content": false,
    "popover-content-id": "popoverSampleContent",
    "popover-title": false,
    "header-text": "Lorem ipsum dolor sit amet",
    "popover-trigger": "manual",
    "item-list": [
          {
          "item-list-class": "a-dotted a-inactive",
          "item-list-title": "<b>Ei sit zril ponderum</b>"
          },
          {
          "item-list-class": "a-dotted a-inactive",
          "item-list-title": "— No stet percipit pri, erat quando eam et."
    }]
  }
}