{
  "msg-forwarded": {
    "extra-class-headingContent": "a-compact a-forwarded",
    "due-date-content": false,
    "shortcuts": {
      "shortcut-icons": [
        {
          "button-text": false,
          "button-class": "a-btn a-btn-icon justify-content-center p-0 m-0 mr-1",
          "button-icon": {
            "icon-prefix": "ai",
            "icon-class": "ai-archive",
            "icon-size": "ai-sm",
            "icon-extra-class": "ai-nw"
          }
        },
        {
          "button-text": false,
          "button-class": "a-btn a-btn-icon justify-content-center p-0 m-0 mr-1",
          "button-icon": {
            "icon-prefix": "ai",
            "icon-class": "ai-forward",
            "icon-size": "ai-sm",
            "icon-extra-class": "ai-nw"
          }
        },
        {
          "button-text": false,
          "button-class": "a-btn a-btn-icon justify-content-center p-0 m-0",
          "button-icon": {
            "icon-prefix": "ai",
            "icon-class": "ai-trash",
            "icon-size": "ai-sm",
            "icon-extra-class": "ai-nw"
          }
        }
      ]
    }
  }
}