{
	"title" : "Altinn",
	"bodyClass" : "a-bgWhite",
	"article-search" : {
		"isLarge" : "a-form-group-large",
		"isHidden" : "sr-only",
		"text-input-label" : "Søk etter innhold",
		"text-input-placeholder" : "Søk etter guider og annet innhold",
		"isInput-group" : "input-group",
		"form-label-class" : "input-group-addon",
		"form-input-hasButton-class": "a-form-control-withBtn form-control-noAddon",
		"form-input-hasButton" : {
      "form-input-button-action" : "Utfør søk",
      "icon-prefix": "tmp",
      "icon-class" : "tmp-search"
		}
	},
	"articlestart" : {
		"page-title" : "Starte og registrere enkeltpersonforetak",
		"byline-tekst": "Sist oppdatert",
	  "byline-dato": "23.01.2017",
		"byline-link" : false,
		"lead-text-content" : "Når du skal registrere et enkeltpersonforetak må du velge foretaksnavn og beskrive virksomheten du skal drive. Er du usikker på om enkeltpersonforetak er riktig for deg kan du lese om valg av organisasjonsform (lenker kan ikke være i ingressen) og skillet mellom arbeidstakere og næringsdrivende.",
		"breadcrumb-item" : [
			{
				"breadcrumb-title" : "Starte og drive bedrift",
				"breadcrumb-link" : "link.sider-seksjonsforside-v-starteogdrive"
			},
			{
				"breadcrumb-title" : "Starte bedrift",
				"breadcrumb-link" : "link.sider-temaside-v-starte",
				"breadcrumb-class" : "breadcrumb-mobile"
			},
			{
				"breadcrumb-title" : "Starte og registrere enkeltpersonforetak",
				"breadcrumb-class" : "active"
			}
		]
	},

	"firstpart" : {
		"sectiontitle1" : {
			"section-title": ""
		},
		"list1" : {

			"bulletListItems" : [
		    {
		      "listItemDescription" : "Planlegge å drive <a href=\"#\" class=\"a-linkArea\">næringsvirksomhet</a>"
		    },
				{
		      "listItemDescription" : "Ha en norsk forretningsadresse",
					"listItemFootnote" : {
						"popover-class": "",
						"footnote-data-target": "myFootnote2",
						"footnote-title": "",
						"footnote-content": "Forretningsadressen må være en norsk fysisk adresse og oppgis med gate eller vei, husnummer, postnummer og sted (ikke postboks)"
					}
			  },
				{
		      "listItemDescription" : "Ha fylt 18 år",
					"listItemFootnote" : {
						"popover-class": "",
						"footnote-data-target": "myFootnote4",
						"footnote-title": "",
						"footnote-content": "Hvis du er over 15 år kan du registrere enkeltpersonforetak etter tillatelse fra foresatte/verge og Fylkesmannen"
					}
			  },
		    {
					"listItemDescription" : "Hvis du ikke er statsborger i et EU/EØS-land, og planlegger å drive virksomhet i Norge må du undersøke reglene for <a href=\"#\" class=\"a-linkArea\">oppholdstillatelse</a>."
		    }
		  ]

		},

		"list2" : {

			"connectedBullets-list-items" : [
		    {
		      "list-item-content" : "Registrer enkeltpersonforetak ved å fylle ut skjemaet <br>",
		      "list-item-linkInside": true,
		      "link-class": "a-link",
		      "link-text": "Samordnet registermelding",
		      "link-icon": {
		        "icon-prefix": "ai",
		        "icon-class": "ai-arrowright",
		        "icon-extra-class": "a-link-arrow"
		      }
		    },
		    {
					"list-item-content" : "Hvis du har avtale med regnskapsfører må dette bekreftes ved at regnskapsfører signerer elektronisk. Hvis du har revisor må dette bekreftes ved at det lastes opp en villighetserklæring og at revisor signerer elektronisk.",
		      "list-item-linkInside": false
		    },
				{
		      "list-item-content" : "Når foretaket er registrert får innsender beskjed om dette i «Min meldingsboks».",
		      "list-item-linkInside": false
		    }

			]

		},

		"firstlink" : {
			"link-text": "Om elektronisk signering",
		  "link-class": "a-link",
		  "link-icon": {
		    "icon-prefix": "ai",
		    "icon-class" : "ai-arrowright"
		  }
		},



		"list3" : {

			"connectedBullets-list-items" : [
		    {
		      "list-item-content" : "Registrer enkeltpersonforetak ved å fylle ut og signere papirblankettene <a href=\"#\" class=\"a-linkArea\">Søknad om D-nummer</a> og <a href=\"#\" class=\"a-linkArea\">skjema for registrering av enkeltpersonforetak</a>  (Forenklet registermelding – blankett for enkeltpersonforetak). ",
		      "list-item-linkInside": false
		    },
		    {
					"list-item-content" : "Send skjemaene samlet til postadressen som står oppgitt på skjemaet. Legg ved bekreftet kopi av gyldig legitimasjon.",
		      "list-item-linkInside": false
		    },
				{
					"list-item-content" : "Når d-nummer er tildelt og registreringen er ferdig behandlet sendes svaret til innsender.",
		      "list-item-linkInside": false
		    }
			]

		},
		"link2" : {
			"link-text": "Oversikt over saksbehandlingstider",
		  "link-class": "a-link",
		  "link-icon": {
		    "icon-prefix": "ai",
		    "icon-class" : "ai-arrowright"
		  }
		},
		"link3" : {
			"link-text": "Informasjon om drift av enkeltpersonforetak",
		  "link-class": "a-link",
		  "link-icon": {
		    "icon-prefix": "ai",
		    "icon-class" : "ai-arrowright"
		  }
		}

	},

	"footnote1" : {
		"footnote-data-target" : "myFootnote4",
	  "popover-class": "",
	  "footnote-title": "",
	  "footnote-content" : "Enkeltpersonforetak som skal drive med varesalg eller ha mer enn 5 ansatte må registreres i Foretaksregisteret. Dette koster kr 2 250,- (eller 2 832,- for innehavere uten norsk fødselsnummer/D-nummer)",
	  "icon-list": [
	    {
	      "icon-prefix": "tmp",
	      "icon-class" : "tmp-plus"
	    },
	    {
	      "icon-prefix": "tmp",
	      "icon-class" : "tmp-minus"
	    }
	  ]
	},

	"radio-legend" : {
		"radio-legendText" : "Fant du det du lette etter?"
	},

	"radiobuttons" :  [
		{
			"radiobutton-title" : "Ja",
			"radiobutton-id" : "radio1"
		},
		{
			"radiobutton-title" : "Nei",
			"radiobutton-id" : "radio2"
		}
	],

	"cardbottom" : false,

	"picturecontent" : false

}
