{
	"title" : "Profil - Introduksjon",
	"bodyClass": "ap-profile",
	"ap-nav-1-active" : "",
	"ap-nav-2-active" : "",
	"ap-nav-3-active" : "",
	"ap-nav-4-active" : "",
	"ap-nav-4-1-active" : "ap-nav-active",
	"ap-nav-4-2-active" : "",
	"ap-nav-4-3-active" : "",
	"ap-nav-4-4-active" : "",
	"ap-nav-4-5-active" : "",
	"ap-nav-4-6-active" : "",
	"ap-nav-4-7-active" : "",
	"ap-nav-4-8-active" : "",
	"ap-nav-5-active" : "",
	"ap-nav-forceDisplay" : "is-active",
	"article" : [
		{
			"img": {
				"landscape-16x9": {
					"src": "",
					"alt": ""
				}
			},
			"article-title" : "Farger for web",
			"article-intro" : "",
			"article-content" : "",
			"article-links" : [
				{
					"article-links-title" : "This is a link",
					"article-links-url" : "http://vg.no"
				},
				{
					"article-links-title" : "This is a second link",
					"article-links-url" : "http://vg.no"
				}
			],
			"article-social" : "Her kommer sosialt"
		}
	]
}
